amw/__init__.py
amw/core/__init__.py
amw/core/arclink_client.py
amw/core/signal_utils.py
amw/core/utils.py
amw/mw/MinimizeInGrid.py
amw/mw/__init__.py
amw/mw/double_phase_mw.py
amw/mw/estimation.py
amw/mw/parameters.py
amw/mw/plot.py
amw/mw/single_phase_mw.py
amw/mw/source_models.py
amw/mw/spectral_mw.py
amw/mw/test_greens_function.py
amw/mw/utils.py
amw-0.0.3.dist-info/LICENSE
amw-0.0.3.dist-info/METADATA
amw-0.0.3.dist-info/WHEEL
amw-0.0.3.dist-info/entry_points.txt
amw-0.0.3.dist-info/top_level.txt
amw-0.0.3.dist-info/RECORD
