Metadata-Version: 2.1
Name: amw
Version: 0.0.3
Summary: Earthquake moment magnitude estimation from P, S or common P and S waves
Home-page: https://github.com/JanWiszniowski/amw
Author: Jan Wiszniowski
Author-email: jwisz@igf.edu.pl
License: GNU Lesser General Public License, Version 3
Keywords: seismology,moment magnitude,anthropogenic seismicity,near field,intermediate field
Platform: UNKNOWN
Classifier: Development Status :: 3 - Alpha
Classifier: Intended Audience :: Developers
Classifier: License :: OSI Approved :: GNU Lesser General Public License v3 (LGPLv3)
Classifier: Programming Language :: Python :: 3
Classifier: Programming Language :: Python :: 3.9
License-File: LICENSE
Requires-Dist: matplotlib (>=3.9.2)
Requires-Dist: obspy (>=1.2.0)
Requires-Dist: future (>=1.0.0)
